LICENSE
README.md
setup.cfg
setup.py
apple_heartrate_pandas/__init__.py
apple_heartrate_pandas/_version.py
apple_heartrate_pandas/utils.py
apple_heartrate_pandas.egg-info/PKG-INFO
apple_heartrate_pandas.egg-info/SOURCES.txt
apple_heartrate_pandas.egg-info/dependency_links.txt
apple_heartrate_pandas.egg-info/requires.txt
apple_heartrate_pandas.egg-info/top_level.txt