Metadata-Version: 2.1
Name: apple-heartrate-pandas
Version: 0.1.6
Summary: A Python package to convert Apple Health Heartrate in Pandas
Home-page: https://github.com/LeonardoAlchieri/apple-heartrate-pandas
Author: Leonardo Alchieri
Author-email: leonardo@alchieri.eu
License: MIT
Keywords: apple,health,heartrate,pandas
Platform: UNKNOWN
Classifier: Programming Language :: Python
Classifier: Programming Language :: Python :: 3.7
Classifier: Programming Language :: Python :: 3.8
Classifier: Programming Language :: Python :: 3.9
Classifier: Programming Language :: Python :: 3 :: Only
Classifier: Development Status :: 4 - Beta
Classifier: Environment :: Console
Classifier: Intended Audience :: Developers
Classifier: Intended Audience :: Science/Research
Classifier: License :: OSI Approved :: MIT License
Classifier: Topic :: Scientific/Engineering
Classifier: Topic :: Scientific/Engineering :: Human Machine Interfaces
Requires-Python: >=3.7
License-File: LICENSE
